panpython/__init__.py
panpython/pan_sdk/__init__.py
panpython/pan_sdk/stat/__init__.py
panpython/pan_sdk/stat/clean_merged_csv_form_htc_point.py
panpython/pan_sdk/widgets/__init__.py
panpython/pan_sdk/widgets/htc_visualizer.py
panpython-0.0.1.dist-info/LICENSE
panpython-0.0.1.dist-info/METADATA
panpython-0.0.1.dist-info/WHEEL
panpython-0.0.1.dist-info/top_level.txt
panpython-0.0.1.dist-info/RECORD
