Metadata-Version: 2.1
Name: panpython
Version: 0.0.1
Summary: a SDK for Pandat applications
Home-page: https://github.com/andrewlyu/panpython
Author: Duchao Lv
Author-email: duchaolv@gmail.com
License: UNKNOWN
Platform: UNKNOWN
Classifier: Programming Language :: Python :: 3
Classifier: License :: OSI Approved :: MIT License
Classifier: Operating System :: OS Independent
Requires-Python: >=3.6
